spin_pulse/__init__.py
spin_pulse/version.py
spin_pulse/characterization/__init__.py
spin_pulse/characterization/average_superop.py
spin_pulse/characterization/ramsey.py
spin_pulse/environment/__init__.py
spin_pulse/environment/experimental_environment.py
spin_pulse/environment/noise/__init__.py
spin_pulse/environment/noise/noise_time_trace.py
spin_pulse/environment/noise/pink.py
spin_pulse/environment/noise/quasistatic.py
spin_pulse/environment/noise/white.py
spin_pulse/transpilation/__init__.py
spin_pulse/transpilation/dynamical_decoupling.py
spin_pulse/transpilation/hardware_specs.py
spin_pulse/transpilation/pulse_circuit.py
spin_pulse/transpilation/pulse_layer.py
spin_pulse/transpilation/pulse_sequence.py
spin_pulse/transpilation/utils.py
spin_pulse/transpilation/instructions/__init__.py
spin_pulse/transpilation/instructions/idle.py
spin_pulse/transpilation/instructions/pulse_instruction.py
spin_pulse/transpilation/instructions/rotations.py
spin_pulse/transpilation/passes/__init__.py
spin_pulse/transpilation/passes/rzz_echo.py
spin_pulse-1.0.2.dist-info/licenses/LICENCE.txt
spin_pulse-1.0.2.dist-info/METADATA
spin_pulse-1.0.2.dist-info/WHEEL
spin_pulse-1.0.2.dist-info/top_level.txt
spin_pulse-1.0.2.dist-info/RECORD
