Metadata-Version: 2.4
Name: spin_pulse
Version: 1.0.2
Summary: Quobly noise accurate simulation toolbox.
Author-email: Benoit Vermersch <benoit.vermersch@quobly.io>, Oscar Gravier <oscar.gravier@gmail.com>, "Matthieu C. Dartiailh" <matthieu.dartiailh@quobly.io>, Julia Guignon <julia.guignon@quobly.io>, Nathan Miscopein <nathan.miscopein@quobly.io>, Carlos Ramos Marimon <carlos.marimon@quobly.io>, Jonathan Durandau <jonathan.durandau@quobly.io>, Tristan Meunier <tristan.meunier@quobly.io>, Valentin Savin <valentin.savin@quobly.io>
Project-URL: homepage, https://github.com/quobly-sw/SpinPulse
Project-URL: repository, https://github.com/quobly-sw/SpinPulse
Classifier: Programming Language :: Python
Classifier: Programming Language :: Python :: 3.11
Classifier: Programming Language :: Python :: 3.12
Classifier: Programming Language :: Python :: 3.13
Classifier: Programming Language :: Python :: Implementation :: CPython
Classifier: License :: OSI Approved :: Apache Software License
Classifier: Intended Audience :: Science/Research
Classifier: Operating System :: OS Independent
Requires-Python: >=3.11
License-File: LICENCE.txt
Requires-Dist: numpy>=2.1
Requires-Dist: scipy
Requires-Dist: matplotlib
Requires-Dist: qiskit>=2
Requires-Dist: pylatexenc
Requires-Dist: importlib_metadata>=8.7
Requires-Dist: tqdm
Requires-Dist: packaging
Requires-Dist: setuptools_scm
Requires-Dist: qiskit-aer
Requires-Dist: networkx>=3.0
Requires-Dist: llvmlite>=0.46
Requires-Dist: numba>=0.63
Requires-Dist: quimb>=1.10
Dynamic: license-file
